setup.cfg
setup.py
diffr/__init__.py
diffr/data_model.py
diffr/diff.py
diffr/patch.py
diffr.egg-info/PKG-INFO
diffr.egg-info/SOURCES.txt
diffr.egg-info/dependency_links.txt
diffr.egg-info/requires.txt
diffr.egg-info/top_level.txt
test/test_data_model.py
test/test_diff.py
test/test_patch.py