Metadata-Version: 1.1
Name: diffr
Version: 1.1
Summary: Diff and patch Python data structures
Home-page: https://github.com/grahamegee/differ
Author: Grahame Gardiner
Author-email: grahamegee@gmail.com
License: MIT
Download-URL: https://github.com/grahamegee/diffr/releases/tag/1.1
Keywords: diff,diffing,test
Platform: UNKNOWN
Classifier: Development Status :: 5 - Production/Stable
Classifier: Intended Audience :: Developers
Classifier: License :: OSI Approved :: MIT License
Classifier: Natural Language :: English
Classifier: Programming Language :: Python :: 2.7
Classifier: Programming Language :: Python :: 3
Classifier: Topic :: Software Development :: Libraries :: Python Modules
Classifier: Topic :: Software Development :: Testing
